virtual_ecosystem/__init__.py
virtual_ecosystem/core/__init__.py
virtual_ecosystem/core/axes.py
virtual_ecosystem/core/base_model.py
virtual_ecosystem/core/config_builder.py
virtual_ecosystem/core/configuration.py
virtual_ecosystem/core/core_components.py
virtual_ecosystem/core/data.py
virtual_ecosystem/core/exceptions.py
virtual_ecosystem/core/grid.py
virtual_ecosystem/core/logger.py
virtual_ecosystem/core/model_config.py
virtual_ecosystem/core/module_schema.json
virtual_ecosystem/core/readers.py
virtual_ecosystem/core/registry.py
virtual_ecosystem/core/utils.py
virtual_ecosystem/core/variables.py
virtual_ecosystem/core/variables_schema.json
virtual_ecosystem/data_variables.toml
virtual_ecosystem/entry_points.py
virtual_ecosystem/example_data/__init__.py
virtual_ecosystem/example_data/config/animal_config.toml
virtual_ecosystem/example_data/config/data_config.toml
virtual_ecosystem/example_data/config/plant_config.toml
virtual_ecosystem/example_data/config/soil_microbial_groups.toml
virtual_ecosystem/example_data/config/ve_run.toml
virtual_ecosystem/example_data/data/animal_functional_groups.csv
virtual_ecosystem/example_data/data/example_climate_data.nc
virtual_ecosystem/example_data/data/example_elevation_data.nc
virtual_ecosystem/example_data/data/example_litter_data.nc
virtual_ecosystem/example_data/data/example_plant_cohorts.csv
virtual_ecosystem/example_data/data/example_plant_data.nc
virtual_ecosystem/example_data/data/example_soil_data.nc
virtual_ecosystem/example_data/data/plant_pfts.csv
virtual_ecosystem/example_data/generation_scripts/ERA5_land_example.nc
virtual_ecosystem/example_data/generation_scripts/__init__.py
virtual_ecosystem/example_data/generation_scripts/climate_example_data.py
virtual_ecosystem/example_data/generation_scripts/common.py
virtual_ecosystem/example_data/generation_scripts/elevation_example_data.py
virtual_ecosystem/example_data/generation_scripts/litter_example_data.py
virtual_ecosystem-0.1.1a15.dist-info/METADATA
virtual_ecosystem-0.1.1a15.dist-info/WHEEL
virtual_ecosystem-0.1.1a15.dist-info/entry_points.txt
virtual_ecosystem-0.1.1a15.dist-info/licenses/LICENSE
virtual_ecosystem-0.1.1a15.dist-info/RECORD
