Metadata-Version: 2.4
Name: virtual_ecosystem
Version: 0.1.1a15
Summary: An holistic ecosystem simulation model.
License-Expression: BSD-3-Clause
License-File: LICENSE
Author: Rob Ewers
Author-email: r.ewers@imperial.ac.uk
Requires-Python: >=3.11
Classifier: Development Status :: 2 - Pre-Alpha
Classifier: Intended Audience :: Science/Research
Classifier: License :: OSI Approved :: BSD License
Classifier: Topic :: Scientific/Engineering
Requires-Dist: Shapely (>2.0)
Requires-Dist: dask (>2023.6)
Requires-Dist: dpath (>2.0)
Requires-Dist: netcdf4 (>1.6)
Requires-Dist: numpy (>2.0)
Requires-Dist: openpyxl (>3.1)
Requires-Dist: pint (>0.24)
Requires-Dist: pydantic (>=2.12.0,<3.0.0)
Requires-Dist: pyrealm (>=2.0.0rc5)
Requires-Dist: scipy (>1.12)
Requires-Dist: tomli-w (>1.0)
Requires-Dist: tqdm (>4.66)
Requires-Dist: types-tabulate (>0.9)
Requires-Dist: xarray (>2024.6)
Project-URL: Homepage, https://virtual-ecosystem.readthedocs.io/
Project-URL: Repository, https://github.com/ImperialCollegeLondon/virtual_ecosystem
